dxtr/__init__.py
dxtr/cochains/__init__.py
dxtr/cochains/cochain.py
dxtr/cochains/example_cochains.py
dxtr/cochains/whitneymap.py
dxtr/complexes/__init__.py
dxtr/complexes/abstractsimplicialcomplex.py
dxtr/complexes/example_complexes.py
dxtr/complexes/module.py
dxtr/complexes/simplex.py
dxtr/complexes/simplicialcomplex.py
dxtr/complexes/simplicialmanifold.py
dxtr/io/__init__.py
dxtr/io/read.py
dxtr/io/write.py
dxtr/math/__init__.py
dxtr/math/geometry.py
dxtr/math/topology.py
dxtr/operators/__init__.py
dxtr/operators/curvature.py
dxtr/operators/differential.py
dxtr/operators/hodge.py
dxtr/operators/musical.py
dxtr/operators/wedge.py
dxtr/utils/__init__.py
dxtr/utils/logging.py
dxtr/utils/quality_control.py
dxtr/utils/typecheck.py
dxtr/utils/wrappers.py
dxtr/utils/mesh_examples/disk_large.ply
dxtr/utils/mesh_examples/disk_massive.ply
dxtr/utils/mesh_examples/disk_small.ply
dxtr/utils/mesh_examples/icosahedron_complex.vtk
dxtr/utils/mesh_examples/icosahedron_unit_0_cochain.vtk
dxtr/utils/mesh_examples/icosahedron_unit_1_cochain.vtk
dxtr/utils/mesh_examples/icosahedron_unit_2_cochain.vtk
dxtr/utils/mesh_examples/sphere_large.ply
dxtr/utils/mesh_examples/sphere_massive.ply
dxtr/utils/mesh_examples/sphere_medium.ply
dxtr/utils/mesh_examples/sphere_small.ply
dxtr/visu/__init__.py
dxtr/visu/visu_plotly.py
dxtr/visu/visu_pyvista.py
dxtr/visu/visualize.py
dxtr-1.0.0.dist-info/licenses/LICENSE.md
dxtr-1.0.0.dist-info/METADATA
dxtr-1.0.0.dist-info/WHEEL
dxtr-1.0.0.dist-info/top_level.txt
dxtr-1.0.0.dist-info/RECORD
