Metadata-Version: 2.4
Name: dxtr
Version: 1.0.0
Summary: Discrete Exterior Calculus library in Python.
Author-email: Olivier Ali <olivier.ali@inria.fr>
License: # GNU GENERAL PUBLIC LICENSE
Project-URL: homepage, https://oali.gitlabpages.inria.fr/dxtr
Project-URL: repository, https://gitlab.inria.fr/oali/dxtr
Project-URL: issues, https://gitlab.inria.fr/oali/dxtr/issues
Classifier: Development Status :: 4 - Beta
Classifier: Intended Audience :: Developers
Classifier: Intended Audience :: Science/Research
Classifier: License :: OSI Approved :: GNU General Public License v3 or later (GPLv3+)
Classifier: Natural Language :: English
Classifier: Operating System :: MacOS
Classifier: Operating System :: Microsoft :: Windows
Classifier: Operating System :: POSIX
Classifier: Operating System :: Unix
Classifier: Programming Language :: Python :: 3 :: Only
Classifier: Programming Language :: Python :: 3.9
Classifier: Programming Language :: Python :: 3.10
Classifier: Programming Language :: Python :: 3.11
Classifier: Programming Language :: Python :: 3.12
Classifier: Topic :: Scientific/Engineering :: Bio-Informatics
Classifier: Topic :: Scientific/Engineering :: Image Processing
Classifier: Topic :: Scientific/Engineering
Requires-Python: <3.13,>=3.9
License-File: LICENSE.md
Requires-Dist: numpy
Requires-Dist: scipy
Requires-Dist: sparse
Requires-Dist: pandas
Requires-Dist: plotly<6.0.0
Requires-Dist: statsmodels
Requires-Dist: pyvista
Requires-Dist: trame
Requires-Dist: meshio
Provides-Extra: doc
Requires-Dist: mkdocs; extra == "doc"
Requires-Dist: mkdocs-material; extra == "doc"
Requires-Dist: mkdocs-gen-files; extra == "doc"
Requires-Dist: mkdocs-autorefs; extra == "doc"
Requires-Dist: mkdocs-get-deps; extra == "doc"
Requires-Dist: mkdocs-jupyter; extra == "doc"
Requires-Dist: mkdocs-literate-nav; extra == "doc"
Requires-Dist: mkdocs-material-extensions; extra == "doc"
Requires-Dist: mkdocstrings; extra == "doc"
Requires-Dist: mkdocstrings-python; extra == "doc"
Requires-Dist: mkdocs-mermaid2-plugin; extra == "doc"
Requires-Dist: mkdocs-gen-files; extra == "doc"
Requires-Dist: python-markdown-math; extra == "doc"
Provides-Extra: test
Requires-Dist: pytest; extra == "test"
Requires-Dist: pytest-cov; extra == "test"
Provides-Extra: nb
Requires-Dist: jupyter; extra == "nb"
Requires-Dist: ipywidgets; extra == "nb"
Requires-Dist: nbconvert; extra == "nb"
Dynamic: license-file
